{
  "schemaVersion": 1,
  "generatedAt": "2026-06-25T11:14:58.341Z",
  "sourceFile": "Hohenzollernradweg_Relax.gpx",
  "tourStartDateTime": "2026-07-01T09:00:00+02:00",
  "valid": true,
  "reason": null,
  "provider": {
    "weather": "open-meteo",
    "ai": "groq"
  },
  "global": {
    "summary": "Für den Hohenzollernradweg (Relax) ist am Mittwoch bei Temperaturen zwischen 15,5°C und 18,3°C mit Regen zu rechnen, insbesondere in den ersten 60 Kilometern, wo bis zu 3,3 mm Niederschlag erwartet werden. Die Regenwahrscheinlichkeit liegt zwischen 31% und 46%, wobei die höchste Wahrscheinlichkeit im Bereich von km 30 bis km 60 besteht. Der Wind weht mit Geschwindigkeiten zwischen 2 km/h und 14,1 km/h, wobei die stärksten Winde gegen Abend auftreten. Ab etwa km 120 und nachts lässt der Regen nach, und die Temperaturen bleiben relativ konstant. Für die Fahrt ist es ratsam, Regenkleidung und entsprechende Ausrüstung mitzuführen."
  },
  "points": [
    {
      "km": 0,
      "localKm": 0,
      "stageId": 1,
      "stageIndex": 0,
      "stageName": "Stuttgart → Bebenhausen",
      "lat": 48.786032,
      "lon": 9.182346,
      "ele": 249,
      "time": "2026-07-01T07:00:00.000Z",
      "weather": {
        "weatherTime": "2026-07-01T07:00Z",
        "temperature": 17.5,
        "precipitation": 1.9,
        "precipitationProbability": 44,
        "windSpeed": 11.2,
        "weatherCode": 81
      }
    },
    {
      "km": 10,
      "localKm": 10,
      "stageId": 1,
      "stageIndex": 0,
      "stageName": "Stuttgart → Bebenhausen",
      "lat": 48.762968,
      "lon": 9.266779,
      "ele": 227,
      "time": "2026-07-01T07:39:24.005Z",
      "weather": {
        "weatherTime": "2026-07-01T08:00Z",
        "temperature": 17.6,
        "precipitation": 1.9,
        "precipitationProbability": 45,
        "windSpeed": 11.2,
        "weatherCode": 81
      }
    },
    {
      "km": 20,
      "localKm": 20,
      "stageId": 1,
      "stageIndex": 0,
      "stageName": "Stuttgart → Bebenhausen",
      "lat": 48.715868,
      "lon": 9.344141,
      "ele": 249,
      "time": "2026-07-01T08:18:47.050Z",
      "weather": {
        "weatherTime": "2026-07-01T08:00Z",
        "temperature": 17.4,
        "precipitation": 1.8,
        "precipitationProbability": 45,
        "windSpeed": 10.2,
        "weatherCode": 61
      }
    },
    {
      "km": 30,
      "localKm": 30,
      "stageId": 1,
      "stageIndex": 0,
      "stageName": "Stuttgart → Bebenhausen",
      "lat": 48.664723,
      "lon": 9.285157,
      "ele": 400,
      "time": "2026-07-01T08:58:03.941Z",
      "weather": {
        "weatherTime": "2026-07-01T09:00Z",
        "temperature": 16.1,
        "precipitation": 3.3,
        "precipitationProbability": 46,
        "windSpeed": 7.1,
        "weatherCode": 63
      }
    },
    {
      "km": 40,
      "localKm": 40,
      "stageId": 1,
      "stageIndex": 0,
      "stageName": "Stuttgart → Bebenhausen",
      "lat": 48.621026,
      "lon": 9.217084,
      "ele": 335,
      "time": "2026-07-01T09:37:34.974Z",
      "weather": {
        "weatherTime": "2026-07-01T10:00Z",
        "temperature": 16.7,
        "precipitation": 2.5,
        "precipitationProbability": 44,
        "windSpeed": 7.9,
        "weatherCode": 63
      }
    },
    {
      "km": 50,
      "localKm": 50,
      "stageId": 1,
      "stageIndex": 0,
      "stageName": "Stuttgart → Bebenhausen",
      "lat": 48.604031,
      "lon": 9.108124,
      "ele": 416,
      "time": "2026-07-01T10:16:49.156Z",
      "weather": {
        "weatherTime": "2026-07-01T10:00Z",
        "temperature": 16.7,
        "precipitation": 1.5,
        "precipitationProbability": 44,
        "windSpeed": 9.3,
        "weatherCode": 61
      }
    },
    {
      "km": 60,
      "localKm": 60,
      "stageId": 1,
      "stageIndex": 0,
      "stageName": "Stuttgart → Bebenhausen",
      "lat": 48.54853,
      "lon": 9.073802,
      "ele": 343,
      "time": "2026-07-01T10:56:10.483Z",
      "weather": {
        "weatherTime": "2026-07-01T11:00Z",
        "temperature": 17.2,
        "precipitation": 2.4,
        "precipitationProbability": 44,
        "windSpeed": 8.7,
        "weatherCode": 63
      }
    },
    {
      "km": 70,
      "localKm": 8.4,
      "stageId": 2,
      "stageIndex": 1,
      "stageName": "Bebenhausen → Hechingen",
      "lat": 48.548696,
      "lon": 8.985519,
      "ele": 498,
      "time": "2026-07-01T11:56:56.664Z",
      "weather": {
        "weatherTime": "2026-07-01T12:00Z",
        "temperature": 17.7,
        "precipitation": 0.6,
        "precipitationProbability": 43,
        "windSpeed": 12.7,
        "weatherCode": 61
      }
    },
    {
      "km": 80,
      "localKm": 18.4,
      "stageId": 2,
      "stageIndex": 1,
      "stageName": "Bebenhausen → Hechingen",
      "lat": 48.478779,
      "lon": 8.935614,
      "ele": 352,
      "time": "2026-07-01T12:37:58.438Z",
      "weather": {
        "weatherTime": "2026-07-01T13:00Z",
        "temperature": 18.3,
        "precipitation": 0.3,
        "precipitationProbability": 42,
        "windSpeed": 9.8,
        "weatherCode": 3
      }
    },
    {
      "km": 90,
      "localKm": 28.4,
      "stageId": 2,
      "stageIndex": 1,
      "stageName": "Bebenhausen → Hechingen",
      "lat": 48.439546,
      "lon": 8.92964,
      "ele": 432,
      "time": "2026-07-01T13:19:01.851Z",
      "weather": {
        "weatherTime": "2026-07-01T13:00Z",
        "temperature": 17.7,
        "precipitation": 0.3,
        "precipitationProbability": 42,
        "windSpeed": 9.8,
        "weatherCode": 3
      }
    },
    {
      "km": 100,
      "localKm": 38.4,
      "stageId": 2,
      "stageIndex": 1,
      "stageName": "Bebenhausen → Hechingen",
      "lat": 48.385982,
      "lon": 8.935973,
      "ele": 555,
      "time": "2026-07-01T14:00:05.362Z",
      "weather": {
        "weatherTime": "2026-07-01T14:00Z",
        "temperature": 16.5,
        "precipitation": 0.9,
        "precipitationProbability": 40,
        "windSpeed": 7.9,
        "weatherCode": 61
      }
    },
    {
      "km": 110,
      "localKm": 48.4,
      "stageId": 2,
      "stageIndex": 1,
      "stageName": "Bebenhausen → Hechingen",
      "lat": 48.331262,
      "lon": 8.982852,
      "ele": 556,
      "time": "2026-07-01T14:41:05.334Z",
      "weather": {
        "weatherTime": "2026-07-01T15:00Z",
        "temperature": 16.5,
        "precipitation": 0.9,
        "precipitationProbability": 39,
        "windSpeed": 6.8,
        "weatherCode": 61
      }
    },
    {
      "km": 120,
      "localKm": 9.8,
      "stageId": 3,
      "stageIndex": 2,
      "stageName": "Hechingen → Sigmaringen",
      "lat": 48.326887,
      "lon": 9.035295,
      "ele": 589,
      "time": "2026-07-01T15:40:33.537Z",
      "weather": {
        "weatherTime": "2026-07-01T16:00Z",
        "temperature": 16.3,
        "precipitation": 0.1,
        "precipitationProbability": 37,
        "windSpeed": 6.3,
        "weatherCode": 61
      }
    },
    {
      "km": 130.1,
      "localKm": 19.8,
      "stageId": 3,
      "stageIndex": 2,
      "stageName": "Hechingen → Sigmaringen",
      "lat": 48.289066,
      "lon": 9.128808,
      "ele": 715,
      "time": "2026-07-01T16:20:16.436Z",
      "weather": {
        "weatherTime": "2026-07-01T16:00Z",
        "temperature": 15.5,
        "precipitation": 0.2,
        "precipitationProbability": 46,
        "windSpeed": 14.1,
        "weatherCode": 61
      }
    },
    {
      "km": 140,
      "localKm": 29.8,
      "stageId": 3,
      "stageIndex": 2,
      "stageName": "Hechingen → Sigmaringen",
      "lat": 48.232469,
      "lon": 9.206434,
      "ele": 674,
      "time": "2026-07-01T16:59:29.012Z",
      "weather": {
        "weatherTime": "2026-07-01T17:00Z",
        "temperature": 15.6,
        "precipitation": 0.2,
        "precipitationProbability": 44,
        "windSpeed": 14,
        "weatherCode": 61
      }
    },
    {
      "km": 150,
      "localKm": 39.8,
      "stageId": 3,
      "stageIndex": 2,
      "stageName": "Hechingen → Sigmaringen",
      "lat": 48.206517,
      "lon": 9.219469,
      "ele": 638,
      "time": "2026-07-01T17:39:01.812Z",
      "weather": {
        "weatherTime": "2026-07-01T18:00Z",
        "temperature": 15.5,
        "precipitation": 0.2,
        "precipitationProbability": 41,
        "windSpeed": 12.5,
        "weatherCode": 61
      }
    },
    {
      "km": 160,
      "localKm": 49.8,
      "stageId": 3,
      "stageIndex": 2,
      "stageName": "Hechingen → Sigmaringen",
      "lat": 48.143883,
      "lon": 9.205921,
      "ele": 608,
      "time": "2026-07-01T18:18:26.913Z",
      "weather": {
        "weatherTime": "2026-07-01T18:00Z",
        "temperature": 16.1,
        "precipitation": 0.2,
        "precipitationProbability": 41,
        "windSpeed": 9.7,
        "weatherCode": 61
      }
    },
    {
      "km": 170.1,
      "localKm": 59.9,
      "stageId": 3,
      "stageIndex": 2,
      "stageName": "Hechingen → Sigmaringen",
      "lat": 48.110319,
      "lon": 9.27025,
      "ele": 602,
      "time": "2026-07-01T18:58:11.582Z",
      "weather": {
        "weatherTime": "2026-07-01T19:00Z",
        "temperature": 15.9,
        "precipitation": 0.4,
        "precipitationProbability": 37,
        "windSpeed": 8.4,
        "weatherCode": 61
      }
    },
    {
      "km": 180.1,
      "localKm": 69.8,
      "stageId": 3,
      "stageIndex": 2,
      "stageName": "Hechingen → Sigmaringen",
      "lat": 48.072779,
      "lon": 9.238251,
      "ele": 575,
      "time": "2026-07-01T19:37:33.546Z",
      "weather": {
        "weatherTime": "2026-07-01T20:00Z",
        "temperature": 16,
        "precipitation": 0.4,
        "precipitationProbability": 34,
        "windSpeed": 7.4,
        "weatherCode": 61
      }
    },
    {
      "km": 190,
      "localKm": 6.2,
      "stageId": 4,
      "stageIndex": 3,
      "stageName": "Sigmaringen → Singen",
      "lat": 48.066639,
      "lon": 9.156306,
      "ele": 676,
      "time": "2026-07-01T20:36:44.258Z",
      "weather": {
        "weatherTime": "2026-07-01T21:00Z",
        "temperature": 15.2,
        "precipitation": 0.2,
        "precipitationProbability": 31,
        "windSpeed": 8.2,
        "weatherCode": 61
      }
    },
    {
      "km": 200,
      "localKm": 16.2,
      "stageId": 4,
      "stageIndex": 3,
      "stageName": "Sigmaringen → Singen",
      "lat": 48.004995,
      "lon": 9.137876,
      "ele": 602,
      "time": "2026-07-01T21:15:59.138Z",
      "weather": {
        "weatherTime": "2026-07-01T21:00Z",
        "temperature": 15.6,
        "precipitation": 0.3,
        "precipitationProbability": 31,
        "windSpeed": 4.6,
        "weatherCode": 61
      }
    },
    {
      "km": 210,
      "localKm": 26.2,
      "stageId": 4,
      "stageIndex": 3,
      "stageName": "Sigmaringen → Singen",
      "lat": 47.940579,
      "lon": 9.082799,
      "ele": 612,
      "time": "2026-07-01T21:55:13.803Z",
      "weather": {
        "weatherTime": "2026-07-01T22:00Z",
        "temperature": 15.4,
        "precipitation": 0.1,
        "precipitationProbability": 34,
        "windSpeed": 3.7,
        "weatherCode": 61
      }
    },
    {
      "km": 220,
      "localKm": 36.2,
      "stageId": 4,
      "stageIndex": 3,
      "stageName": "Sigmaringen → Singen",
      "lat": 47.881195,
      "lon": 9.041844,
      "ele": 620,
      "time": "2026-07-01T22:34:29.331Z",
      "weather": {
        "weatherTime": "2026-07-01T23:00Z",
        "temperature": 15.5,
        "precipitation": 0,
        "precipitationProbability": 32,
        "windSpeed": 4.6,
        "weatherCode": 3
      }
    },
    {
      "km": 230,
      "localKm": 46.2,
      "stageId": 4,
      "stageIndex": 3,
      "stageName": "Sigmaringen → Singen",
      "lat": 47.823865,
      "lon": 9.058252,
      "ele": 433,
      "time": "2026-07-01T23:13:40.616Z",
      "weather": {
        "weatherTime": "2026-07-01T23:00Z",
        "temperature": 16.7,
        "precipitation": 0,
        "precipitationProbability": 35,
        "windSpeed": 4.6,
        "weatherCode": 3
      }
    },
    {
      "km": 240,
      "localKm": 56.2,
      "stageId": 4,
      "stageIndex": 3,
      "stageName": "Sigmaringen → Singen",
      "lat": 47.787423,
      "lon": 8.977046,
      "ele": 440,
      "time": "2026-07-01T23:52:53.209Z",
      "weather": {
        "weatherTime": "2026-07-02T00:00Z",
        "temperature": 16.7,
        "precipitation": 0,
        "precipitationProbability": 33,
        "windSpeed": 3.9,
        "weatherCode": 61
      }
    },
    {
      "km": 250.1,
      "localKm": 66.3,
      "stageId": 4,
      "stageIndex": 3,
      "stageName": "Sigmaringen → Singen",
      "lat": 47.740755,
      "lon": 8.934719,
      "ele": 397,
      "time": "2026-07-02T00:32:21.620Z",
      "weather": {
        "weatherTime": "2026-07-02T01:00Z",
        "temperature": 16.3,
        "precipitation": 0,
        "precipitationProbability": 31,
        "windSpeed": 2,
        "weatherCode": 3
      }
    }
  ],
  "stages": [
    {
      "stageId": 1,
      "stageIndex": 0,
      "name": "Stuttgart → Bebenhausen",
      "startKm": 0,
      "endKm": 61.6,
      "summary": "Für die erste Etappe von Stuttgart nach Bebenhausen erwarten wir am Mittwoch bei Start um 09:00 Uhr milde Temperaturen um 17°C. Es besteht eine Regenwahrscheinlichkeit von etwa 44-45% mit Niederschlagsmengen von 1,5-3,3 mm, wobei die stärksten Regenfälle zwischen km 30 und km 40 erwartet werden. Der Wind weht mit etwa 7-11 km/h, wobei die Windgeschwindigkeit im Laufe der Tour leicht schwankt. Insgesamt sollte man für diese etwa 60 km lange Strecke mit einer Fahrtdauer von etwa 4 Stunden auf wechselhaftes Wetter vorbereitet sein.",
      "points": [
        {
          "km": 0,
          "localKm": 0,
          "stageId": 1,
          "stageIndex": 0,
          "stageName": "Stuttgart → Bebenhausen",
          "lat": 48.786032,
          "lon": 9.182346,
          "ele": 249,
          "time": "2026-07-01T07:00:00.000Z",
          "weather": {
            "weatherTime": "2026-07-01T07:00Z",
            "temperature": 17.5,
            "precipitation": 1.9,
            "precipitationProbability": 44,
            "windSpeed": 11.2,
            "weatherCode": 81
          }
        },
        {
          "km": 10,
          "localKm": 10,
          "stageId": 1,
          "stageIndex": 0,
          "stageName": "Stuttgart → Bebenhausen",
          "lat": 48.762968,
          "lon": 9.266779,
          "ele": 227,
          "time": "2026-07-01T07:39:24.005Z",
          "weather": {
            "weatherTime": "2026-07-01T08:00Z",
            "temperature": 17.6,
            "precipitation": 1.9,
            "precipitationProbability": 45,
            "windSpeed": 11.2,
            "weatherCode": 81
          }
        },
        {
          "km": 20,
          "localKm": 20,
          "stageId": 1,
          "stageIndex": 0,
          "stageName": "Stuttgart → Bebenhausen",
          "lat": 48.715868,
          "lon": 9.344141,
          "ele": 249,
          "time": "2026-07-01T08:18:47.050Z",
          "weather": {
            "weatherTime": "2026-07-01T08:00Z",
            "temperature": 17.4,
            "precipitation": 1.8,
            "precipitationProbability": 45,
            "windSpeed": 10.2,
            "weatherCode": 61
          }
        },
        {
          "km": 30,
          "localKm": 30,
          "stageId": 1,
          "stageIndex": 0,
          "stageName": "Stuttgart → Bebenhausen",
          "lat": 48.664723,
          "lon": 9.285157,
          "ele": 400,
          "time": "2026-07-01T08:58:03.941Z",
          "weather": {
            "weatherTime": "2026-07-01T09:00Z",
            "temperature": 16.1,
            "precipitation": 3.3,
            "precipitationProbability": 46,
            "windSpeed": 7.1,
            "weatherCode": 63
          }
        },
        {
          "km": 40,
          "localKm": 40,
          "stageId": 1,
          "stageIndex": 0,
          "stageName": "Stuttgart → Bebenhausen",
          "lat": 48.621026,
          "lon": 9.217084,
          "ele": 335,
          "time": "2026-07-01T09:37:34.974Z",
          "weather": {
            "weatherTime": "2026-07-01T10:00Z",
            "temperature": 16.7,
            "precipitation": 2.5,
            "precipitationProbability": 44,
            "windSpeed": 7.9,
            "weatherCode": 63
          }
        },
        {
          "km": 50,
          "localKm": 50,
          "stageId": 1,
          "stageIndex": 0,
          "stageName": "Stuttgart → Bebenhausen",
          "lat": 48.604031,
          "lon": 9.108124,
          "ele": 416,
          "time": "2026-07-01T10:16:49.156Z",
          "weather": {
            "weatherTime": "2026-07-01T10:00Z",
            "temperature": 16.7,
            "precipitation": 1.5,
            "precipitationProbability": 44,
            "windSpeed": 9.3,
            "weatherCode": 61
          }
        },
        {
          "km": 60,
          "localKm": 60,
          "stageId": 1,
          "stageIndex": 0,
          "stageName": "Stuttgart → Bebenhausen",
          "lat": 48.54853,
          "lon": 9.073802,
          "ele": 343,
          "time": "2026-07-01T10:56:10.483Z",
          "weather": {
            "weatherTime": "2026-07-01T11:00Z",
            "temperature": 17.2,
            "precipitation": 2.4,
            "precipitationProbability": 44,
            "windSpeed": 8.7,
            "weatherCode": 63
          }
        }
      ]
    },
    {
      "stageId": 2,
      "stageIndex": 1,
      "name": "Bebenhausen → Hechingen",
      "startKm": 61.6,
      "endKm": 110.2,
      "summary": "Für die Etappe 2 von Bebenhausen nach Hechingen erwarten Sie am Mittwoch bei moderaten Temperaturen zwischen 16,5 und 18,3 Grad Celsius wechselhaftes Wetter. Es besteht eine Regenwahrscheinlichkeit von etwa 40-43% mit Niederschlagsmengen von 0,3 bis 0,9 mm, insbesondere im Bereich von km 100 und km 110. Der Wind weht mit Geschwindigkeiten zwischen 6,8 und 12,7 km/h, wobei die stärksten Böen im ersten Teil der Etappe zu erwarten sind. Ab km 100 lässt der Wind nach, was die Fahrt angenehmer machen dürfte.",
      "points": [
        {
          "km": 70,
          "localKm": 8.4,
          "stageId": 2,
          "stageIndex": 1,
          "stageName": "Bebenhausen → Hechingen",
          "lat": 48.548696,
          "lon": 8.985519,
          "ele": 498,
          "time": "2026-07-01T11:56:56.664Z",
          "weather": {
            "weatherTime": "2026-07-01T12:00Z",
            "temperature": 17.7,
            "precipitation": 0.6,
            "precipitationProbability": 43,
            "windSpeed": 12.7,
            "weatherCode": 61
          }
        },
        {
          "km": 80,
          "localKm": 18.4,
          "stageId": 2,
          "stageIndex": 1,
          "stageName": "Bebenhausen → Hechingen",
          "lat": 48.478779,
          "lon": 8.935614,
          "ele": 352,
          "time": "2026-07-01T12:37:58.438Z",
          "weather": {
            "weatherTime": "2026-07-01T13:00Z",
            "temperature": 18.3,
            "precipitation": 0.3,
            "precipitationProbability": 42,
            "windSpeed": 9.8,
            "weatherCode": 3
          }
        },
        {
          "km": 90,
          "localKm": 28.4,
          "stageId": 2,
          "stageIndex": 1,
          "stageName": "Bebenhausen → Hechingen",
          "lat": 48.439546,
          "lon": 8.92964,
          "ele": 432,
          "time": "2026-07-01T13:19:01.851Z",
          "weather": {
            "weatherTime": "2026-07-01T13:00Z",
            "temperature": 17.7,
            "precipitation": 0.3,
            "precipitationProbability": 42,
            "windSpeed": 9.8,
            "weatherCode": 3
          }
        },
        {
          "km": 100,
          "localKm": 38.4,
          "stageId": 2,
          "stageIndex": 1,
          "stageName": "Bebenhausen → Hechingen",
          "lat": 48.385982,
          "lon": 8.935973,
          "ele": 555,
          "time": "2026-07-01T14:00:05.362Z",
          "weather": {
            "weatherTime": "2026-07-01T14:00Z",
            "temperature": 16.5,
            "precipitation": 0.9,
            "precipitationProbability": 40,
            "windSpeed": 7.9,
            "weatherCode": 61
          }
        },
        {
          "km": 110,
          "localKm": 48.4,
          "stageId": 2,
          "stageIndex": 1,
          "stageName": "Bebenhausen → Hechingen",
          "lat": 48.331262,
          "lon": 8.982852,
          "ele": 556,
          "time": "2026-07-01T14:41:05.334Z",
          "weather": {
            "weatherTime": "2026-07-01T15:00Z",
            "temperature": 16.5,
            "precipitation": 0.9,
            "precipitationProbability": 39,
            "windSpeed": 6.8,
            "weatherCode": 61
          }
        }
      ]
    },
    {
      "stageId": 3,
      "stageIndex": 2,
      "name": "Hechingen → Sigmaringen",
      "startKm": 110.2,
      "endKm": 183.8,
      "summary": "Für die dritte Etappe von Hechingen nach Sigmaringen erwarten Sie am Mittwochabend wechselhaftes Wetter mit Temperaturen zwischen 15,5 und 16,3 Grad Celsius. Es besteht eine Regenwahrscheinlichkeit von etwa 37 bis 46 Prozent, wobei die Niederschlagsmengen mit maximal 0,4 mm jedoch gering bleiben. Der Wind weht mit Geschwindigkeiten zwischen 6,3 und 14,1 km/h, wobei die stärksten Böen zwischen km 130 und 140 erwartet werden. Die Bedingungen verbessern sich leicht gegen Ende der Etappe, mit abnehmender Regenwahrscheinlichkeit und schwächerem Wind.",
      "points": [
        {
          "km": 120,
          "localKm": 9.8,
          "stageId": 3,
          "stageIndex": 2,
          "stageName": "Hechingen → Sigmaringen",
          "lat": 48.326887,
          "lon": 9.035295,
          "ele": 589,
          "time": "2026-07-01T15:40:33.537Z",
          "weather": {
            "weatherTime": "2026-07-01T16:00Z",
            "temperature": 16.3,
            "precipitation": 0.1,
            "precipitationProbability": 37,
            "windSpeed": 6.3,
            "weatherCode": 61
          }
        },
        {
          "km": 130.1,
          "localKm": 19.8,
          "stageId": 3,
          "stageIndex": 2,
          "stageName": "Hechingen → Sigmaringen",
          "lat": 48.289066,
          "lon": 9.128808,
          "ele": 715,
          "time": "2026-07-01T16:20:16.436Z",
          "weather": {
            "weatherTime": "2026-07-01T16:00Z",
            "temperature": 15.5,
            "precipitation": 0.2,
            "precipitationProbability": 46,
            "windSpeed": 14.1,
            "weatherCode": 61
          }
        },
        {
          "km": 140,
          "localKm": 29.8,
          "stageId": 3,
          "stageIndex": 2,
          "stageName": "Hechingen → Sigmaringen",
          "lat": 48.232469,
          "lon": 9.206434,
          "ele": 674,
          "time": "2026-07-01T16:59:29.012Z",
          "weather": {
            "weatherTime": "2026-07-01T17:00Z",
            "temperature": 15.6,
            "precipitation": 0.2,
            "precipitationProbability": 44,
            "windSpeed": 14,
            "weatherCode": 61
          }
        },
        {
          "km": 150,
          "localKm": 39.8,
          "stageId": 3,
          "stageIndex": 2,
          "stageName": "Hechingen → Sigmaringen",
          "lat": 48.206517,
          "lon": 9.219469,
          "ele": 638,
          "time": "2026-07-01T17:39:01.812Z",
          "weather": {
            "weatherTime": "2026-07-01T18:00Z",
            "temperature": 15.5,
            "precipitation": 0.2,
            "precipitationProbability": 41,
            "windSpeed": 12.5,
            "weatherCode": 61
          }
        },
        {
          "km": 160,
          "localKm": 49.8,
          "stageId": 3,
          "stageIndex": 2,
          "stageName": "Hechingen → Sigmaringen",
          "lat": 48.143883,
          "lon": 9.205921,
          "ele": 608,
          "time": "2026-07-01T18:18:26.913Z",
          "weather": {
            "weatherTime": "2026-07-01T18:00Z",
            "temperature": 16.1,
            "precipitation": 0.2,
            "precipitationProbability": 41,
            "windSpeed": 9.7,
            "weatherCode": 61
          }
        },
        {
          "km": 170.1,
          "localKm": 59.9,
          "stageId": 3,
          "stageIndex": 2,
          "stageName": "Hechingen → Sigmaringen",
          "lat": 48.110319,
          "lon": 9.27025,
          "ele": 602,
          "time": "2026-07-01T18:58:11.582Z",
          "weather": {
            "weatherTime": "2026-07-01T19:00Z",
            "temperature": 15.9,
            "precipitation": 0.4,
            "precipitationProbability": 37,
            "windSpeed": 8.4,
            "weatherCode": 61
          }
        },
        {
          "km": 180.1,
          "localKm": 69.8,
          "stageId": 3,
          "stageIndex": 2,
          "stageName": "Hechingen → Sigmaringen",
          "lat": 48.072779,
          "lon": 9.238251,
          "ele": 575,
          "time": "2026-07-01T19:37:33.546Z",
          "weather": {
            "weatherTime": "2026-07-01T20:00Z",
            "temperature": 16,
            "precipitation": 0.4,
            "precipitationProbability": 34,
            "windSpeed": 7.4,
            "weatherCode": 61
          }
        }
      ]
    },
    {
      "stageId": 4,
      "stageIndex": 3,
      "name": "Sigmaringen → Singen",
      "startKm": 183.8,
      "endKm": 259.7,
      "summary": "Für die Etappe 4 von Sigmaringen nach Singen erwarten wir in der Nacht von Mittwoch auf Donnerstag milde Temperaturen zwischen 15 und 17 Grad Celsius. Es gibt eine geringe Regenwahrscheinlichkeit von etwa 30-35%, jedoch sind nur geringe Niederschlagsmengen von maximal 0,3 mm vorhergesagt. Der Wind weht mit moderaten 3-8 km/h, wobei die Windgeschwindigkeit im Laufe der Nacht leicht abnimmt. Auf den ersten 20 Kilometern dieser Etappe (km 190-210) ist mit den meisten Regentropfen zu rechnen, danach bleibt es trocken.",
      "points": [
        {
          "km": 190,
          "localKm": 6.2,
          "stageId": 4,
          "stageIndex": 3,
          "stageName": "Sigmaringen → Singen",
          "lat": 48.066639,
          "lon": 9.156306,
          "ele": 676,
          "time": "2026-07-01T20:36:44.258Z",
          "weather": {
            "weatherTime": "2026-07-01T21:00Z",
            "temperature": 15.2,
            "precipitation": 0.2,
            "precipitationProbability": 31,
            "windSpeed": 8.2,
            "weatherCode": 61
          }
        },
        {
          "km": 200,
          "localKm": 16.2,
          "stageId": 4,
          "stageIndex": 3,
          "stageName": "Sigmaringen → Singen",
          "lat": 48.004995,
          "lon": 9.137876,
          "ele": 602,
          "time": "2026-07-01T21:15:59.138Z",
          "weather": {
            "weatherTime": "2026-07-01T21:00Z",
            "temperature": 15.6,
            "precipitation": 0.3,
            "precipitationProbability": 31,
            "windSpeed": 4.6,
            "weatherCode": 61
          }
        },
        {
          "km": 210,
          "localKm": 26.2,
          "stageId": 4,
          "stageIndex": 3,
          "stageName": "Sigmaringen → Singen",
          "lat": 47.940579,
          "lon": 9.082799,
          "ele": 612,
          "time": "2026-07-01T21:55:13.803Z",
          "weather": {
            "weatherTime": "2026-07-01T22:00Z",
            "temperature": 15.4,
            "precipitation": 0.1,
            "precipitationProbability": 34,
            "windSpeed": 3.7,
            "weatherCode": 61
          }
        },
        {
          "km": 220,
          "localKm": 36.2,
          "stageId": 4,
          "stageIndex": 3,
          "stageName": "Sigmaringen → Singen",
          "lat": 47.881195,
          "lon": 9.041844,
          "ele": 620,
          "time": "2026-07-01T22:34:29.331Z",
          "weather": {
            "weatherTime": "2026-07-01T23:00Z",
            "temperature": 15.5,
            "precipitation": 0,
            "precipitationProbability": 32,
            "windSpeed": 4.6,
            "weatherCode": 3
          }
        },
        {
          "km": 230,
          "localKm": 46.2,
          "stageId": 4,
          "stageIndex": 3,
          "stageName": "Sigmaringen → Singen",
          "lat": 47.823865,
          "lon": 9.058252,
          "ele": 433,
          "time": "2026-07-01T23:13:40.616Z",
          "weather": {
            "weatherTime": "2026-07-01T23:00Z",
            "temperature": 16.7,
            "precipitation": 0,
            "precipitationProbability": 35,
            "windSpeed": 4.6,
            "weatherCode": 3
          }
        },
        {
          "km": 240,
          "localKm": 56.2,
          "stageId": 4,
          "stageIndex": 3,
          "stageName": "Sigmaringen → Singen",
          "lat": 47.787423,
          "lon": 8.977046,
          "ele": 440,
          "time": "2026-07-01T23:52:53.209Z",
          "weather": {
            "weatherTime": "2026-07-02T00:00Z",
            "temperature": 16.7,
            "precipitation": 0,
            "precipitationProbability": 33,
            "windSpeed": 3.9,
            "weatherCode": 61
          }
        },
        {
          "km": 250.1,
          "localKm": 66.3,
          "stageId": 4,
          "stageIndex": 3,
          "stageName": "Sigmaringen → Singen",
          "lat": 47.740755,
          "lon": 8.934719,
          "ele": 397,
          "time": "2026-07-02T00:32:21.620Z",
          "weather": {
            "weatherTime": "2026-07-02T01:00Z",
            "temperature": 16.3,
            "precipitation": 0,
            "precipitationProbability": 31,
            "windSpeed": 2,
            "weatherCode": 3
          }
        }
      ]
    }
  ],
  "routeName": "Hohenzollernradweg (Relax)",
  "totalDistanceKm": 259.7
}